anvil/__init__.py
anvil/block.py
anvil/chunk.py
anvil/empty_chunk.py
anvil/empty_region.py
anvil/empty_section.py
anvil/errors.py
anvil/legacy.py
anvil/legacy_blocks.json
anvil/raw_section.py
anvil/region.py
anvil_parser-0.9.0.dist-info/LICENSE
anvil_parser-0.9.0.dist-info/METADATA
anvil_parser-0.9.0.dist-info/WHEEL
anvil_parser-0.9.0.dist-info/top_level.txt
anvil_parser-0.9.0.dist-info/RECORD
