Metadata-Version: 2.1
Name: anvil-parser
Version: 0.9.0
Summary: A Minecraft anvil file format parser
Home-page: https://github.com/matcool/anvil-parser
Author: mat
License: UNKNOWN
Platform: UNKNOWN
Classifier: Programming Language :: Python :: 3
Classifier: License :: OSI Approved :: MIT License
Classifier: Operating System :: OS Independent
